pyffmpeg/__init__.py
pyffmpeg/misc.py
pyffmpeg/pseudo_ffprobe.py
pyffmpeg/static/bin/windows/ffmpeg.exe
pyffmpeg_bin-1.8.0.1.dist-info/LICENSE
pyffmpeg_bin-1.8.0.1.dist-info/METADATA
pyffmpeg_bin-1.8.0.1.dist-info/WHEEL
pyffmpeg_bin-1.8.0.1.dist-info/top_level.txt
pyffmpeg_bin-1.8.0.1.dist-info/RECORD
