Metadata-Version: 2.1
Name: pyffmpeg-bin
Version: 1.8.0.1
Summary: FFmpeg wrapper for python
Home-page: https://github.com/deuteronomy-works/pyffmpeg-bin
Author: Amoh - Gyebi Godwin Ampofo Michael
Author-email: amohgyebigodwin@gmail.com
License: UNKNOWN
Keywords: ffmpeg,FFmpeg,audio,pyffmpeg
Platform: UNKNOWN
Classifier: Programming Language :: Python
Classifier: Programming Language :: Python :: 3
Classifier: Development Status :: 5 - Production/Stable
Classifier: Intended Audience :: Developers
Classifier: License :: OSI Approved :: Apache Software License
Classifier: Operating System :: OS Independent
Classifier: Topic :: Software Development :: Libraries :: Python Modules
